convolog.py
convolog-0.0.3.dist-info/LICENSE
convolog-0.0.3.dist-info/METADATA
convolog-0.0.3.dist-info/WHEEL
convolog-0.0.3.dist-info/top_level.txt
convolog-0.0.3.dist-info/RECORD
