Metadata-Version: 2.1
Name: convolog
Version: 0.0.3
Summary: A small package used for creating conversation logs.
Author: domohyes
Classifier: Programming Language :: Python :: 3
Classifier: License :: OSI Approved :: MIT License
Classifier: Operating System :: OS Independent
Requires-Python: >=3.8
License-File: LICENSE
